django_und/__init__.py
django_und/models.py
tests/__init__.py
tests/conftest.py
tests/models.py
tests/test_votes.py
django_und-0.1.1.dist-info/LICENCE.txt
django_und-0.1.1.dist-info/METADATA
django_und-0.1.1.dist-info/WHEEL
django_und-0.1.1.dist-info/top_level.txt
django_und-0.1.1.dist-info/RECORD
