Metadata-Version: 2.1
Name: django-und
Version: 0.1.1
Summary: Django Up and Down, django app to add upvote and downvote to models
Home-page: https://github.com/luxcem/django-und
Author: luxcem
Author-email: a@luxcem.fr
License: UNKNOWN
Platform: UNKNOWN
Requires-Dist: django
Provides-Extra: test
Requires-Dist: pytest; extra == 'test'
Requires-Dist: pytest-cov; extra == 'test'
Requires-Dist: pytest-django; extra == 'test'
Requires-Dist: django-factory-boy; extra == 'test'
Requires-Dist: codecov; extra == 'test'
